ganify/__init__.py
ganify/model.py
ganify/discriminator/__init__.py
ganify/discriminator/critic.py
ganify/discriminator/discriminator.py
ganify/generator/__init__.py
ganify/generator/generator.py
ganify/utilities/__init__.py
ganify/utilities/utils.py
ganify-1.0.10.dist-info/LICENSE
ganify-1.0.10.dist-info/METADATA
ganify-1.0.10.dist-info/WHEEL
ganify-1.0.10.dist-info/top_level.txt
ganify-1.0.10.dist-info/RECORD
