Metadata-Version: 2.1
Name: ganify
Version: 1.0.10
Summary: An Easy way to use GANs for data augmentation
Home-page: https://github.com/arnonbruno/ganify
Author: Arnon Bruno
Author-email: asantos.quantum@gmail.com
License: UNKNOWN
Platform: UNKNOWN
Classifier: Programming Language :: Python :: 3
Classifier: License :: OSI Approved :: MIT License
Classifier: Operating System :: OS Independent
Requires-Python: >=3.6
Requires-Dist: tensorflow (>=2.0.0)
Requires-Dist: pandas (>=0.25)
Requires-Dist: numpy (>=1.16)
Requires-Dist: scikit-learn (>=0.21)
Requires-Dist: matplotlib (>=3.1)
Requires-Dist: tqdm (>=4.15)
